{
	"schemaVersion": 1,
	"id": "force-beacon-load",
	"version": "${version}",
	"name": "Force Beacon Load",
	"description": "This is an example description! Tell everyone what your mod is about!",
	"authors": [
		"Me!"
	],
	"contact": {
		"homepage": "https://fabricmc.net/",
		"sources": "https://github.com/FabricMC/fabric-example-mod"
	},
	"license": "CC0-1.0",
	"icon": "assets/force-beacon-load/icon.png",
	"environment": "*",
	"entrypoints": {
		"main": [
			{
				"value": "name.forcebeaconload.ForceBeaconLoad",
				"adapter": "kotlin"
			}
		],
		"client": [
			{
				"value": "name.forcebeaconload.ForceBeaconLoadClient",
				"adapter": "kotlin"
			}
		]
	},
	"mixins": [
		"force-beacon-load.mixins.json",
		{
			"config": "force-beacon-load.client.mixins.json",
			"environment": "client"
		}
	],
    "accessWidener": "forcebeaconload.accesswidener",
	"depends": {
		"fabricloader": ">=0.17.2",
		"minecraft": "~1.20.1",
		"java": ">=17",
		"fabric-api": "*",
		"fabric-language-kotlin": "*"
	},
	"suggests": {
		"another-mod": "*"
	}
}